atomorph/__init__.py
atomorph/cli.py
atomorph/converter.py
atomorph/utils.py
atomorph-1.0.5.dist-info/licenses/LICENSE
examples/__init__.py
examples/fixed_elements.py
examples/fixed_layers.py
examples/multi_frame.py
examples/fixed_elements_output.vasp/frame_1.vasp
examples/fixed_elements_output.vasp/frame_2.vasp
examples/fixed_elements_output.vasp/frame_3.vasp
examples/fixed_layers_output.vasp/frame_1.vasp
examples/fixed_layers_output.vasp/frame_2.vasp
examples/fixed_layers_output.vasp/frame_3.vasp
tests/__init__.py
tests/test_converter.py
tests/test_fixed_layers.py
tests/test_utils.py
atomorph-1.0.5.dist-info/METADATA
atomorph-1.0.5.dist-info/WHEEL
atomorph-1.0.5.dist-info/entry_points.txt
atomorph-1.0.5.dist-info/top_level.txt
atomorph-1.0.5.dist-info/RECORD
